[{"index": 10586, "class": 2}, {"index": 8178, "class": 1}, {"index": 8390, "class": 1}, {"index": 3524, "class": 0}, {"index": 9390, "class": 1}, {"index": 5967, "class": 1}, {"index": 14199, "class": 2}, {"index": 9608, "class": 1}, {"index": 3730, "class": 0}, {"index": 5599, "class": 1}, {"index": 8484, "class": 1}, {"index": 13354, "class": 2}, {"index": 9729, "class": 1}, {"index": 14379, "class": 2}, {"index": 385, "class": 0}, {"index": 12538, "class": 2}, {"index": 11298, "class": 2}, {"index": 2125, "class": 0}, {"index": 3580, "class": 0}, {"index": 1134, "class": 0}, {"index": 5813, "class": 1}, {"index": 7964, "class": 1}, {"index": 12634, "class": 2}, {"index": 11116, "class": 2}, {"index": 4209, "class": 0}, {"index": 7628, "class": 1}, {"index": 12692, "class": 2}, {"index": 7672, "class": 1}, {"index": 7013, "class": 1}, {"index": 1101, "class": 0}, {"index": 12685, "class": 2}, {"index": 10135, "class": 2}, {"index": 1502, "class": 0}, {"index": 11295, "class": 2}, {"index": 6628, "class": 1}, {"index": 4117, "class": 0}, {"index": 612, "class": 0}, {"index": 11927, "class": 2}, {"index": 575, "class": 0}, {"index": 6997, "class": 1}, {"index": 9342, "class": 1}, {"index": 12905, "class": 2}, {"index": 12294, "class": 2}, {"index": 12077, "class": 2}, {"index": 3061, "class": 0}, {"index": 7972, "class": 1}, {"index": 805, "class": 0}, {"index": 10360, "class": 2}, {"index": 8387, "class": 1}, {"index": 9824, "class": 1}, {"index": 2550, "class": 0}, {"index": 3680, "class": 0}, {"index": 4889, "class": 0}, {"index": 4779, "class": 0}, {"index": 5862, "class": 1}, {"index": 5062, "class": 0}, {"index": 52, "class": 0}, {"index": 6071, "class": 1}, {"index": 10347, "class": 2}, {"index": 7593, "class": 1}, {"index": 7086, "class": 1}, {"index": 3294, "class": 0}, {"index": 8928, "class": 1}, {"index": 11651, "class": 2}, {"index": 2877, "class": 0}, {"index": 1301, "class": 0}, {"index": 8588, "class": 1}, {"index": 9336, "class": 1}, {"index": 10108, "class": 2}, {"index": 11878, "class": 2}, {"index": 2053, "class": 0}, {"index": 12930, "class": 2}, {"index": 10308, "class": 2}, {"index": 6367, "class": 1}, {"index": 6279, "class": 1}, {"index": 9142, "class": 1}, {"index": 6726, "class": 1}, {"index": 10900, "class": 2}, {"index": 13178, "class": 2}, {"index": 6885, "class": 1}, {"index": 1895, "class": 0}, {"index": 1273, "class": 0}, {"index": 7289, "class": 1}, {"index": 3999, "class": 0}, {"index": 12324, "class": 2}, {"index": 12311, "class": 2}, {"index": 3998, "class": 0}, {"index": 10179, "class": 2}, {"index": 860, "class": 0}, {"index": 1931, "class": 0}, {"index": 2933, "class": 0}, {"index": 14013, "class": 2}, {"index": 7745, "class": 1}, {"index": 13961, "class": 2}, {"index": 1621, "class": 0}, {"index": 8283, "class": 1}, {"index": 8819, "class": 1}, {"index": 5726, "class": 1}, {"index": 10182, "class": 2}, {"index": 9208, "class": 1}, {"index": 10412, "class": 2}, {"index": 13352, "class": 2}, {"index": 2286, "class": 0}, {"index": 12384, "class": 2}, {"index": 318, "class": 0}, {"index": 13199, "class": 2}, {"index": 7883, "class": 1}, {"index": 12565, "class": 2}, {"index": 2641, "class": 0}, {"index": 1076, "class": 0}, {"index": 12179, "class": 2}, {"index": 14039, "class": 2}, {"index": 3768, "class": 0}, {"index": 11793, "class": 2}, {"index": 1539, "class": 0}, {"index": 7744, "class": 1}, {"index": 11965, "class": 2}, {"index": 6439, "class": 1}, {"index": 4277, "class": 0}, {"index": 4719, "class": 0}, {"index": 5981, "class": 1}, {"index": 11368, "class": 2}, {"index": 3493, "class": 0}, {"index": 3966, "class": 0}, {"index": 2683, "class": 0}, {"index": 7394, "class": 1}, {"index": 7112, "class": 1}, {"index": 10939, "class": 2}, {"index": 10391, "class": 2}, {"index": 7749, "class": 1}, {"index": 864, "class": 0}, {"index": 4928, "class": 0}, {"index": 10733, "class": 2}, {"index": 14468, "class": 2}, {"index": 4591, "class": 0}, {"index": 8305, "class": 1}, {"index": 5098, "class": 0}, {"index": 336, "class": 0}, {"index": 8229, "class": 1}, {"index": 3106, "class": 0}, {"index": 1786, "class": 0}, {"index": 12975, "class": 2}, {"index": 8374, "class": 1}, {"index": 14415, "class": 2}, {"index": 8441, "class": 1}, {"index": 6941, "class": 1}, {"index": 11394, "class": 2}, {"index": 5663, "class": 1}, {"index": 3464, "class": 0}, {"index": 7714, "class": 1}, {"index": 9524, "class": 1}, {"index": 3323, "class": 0}, {"index": 11417, "class": 2}, {"index": 7552, "class": 1}, {"index": 4379, "class": 0}, {"index": 1545, "class": 0}, {"index": 2726, "class": 0}, {"index": 996, "class": 0}, {"index": 12711, "class": 2}, {"index": 9037, "class": 1}, {"index": 3346, "class": 0}, {"index": 2374, "class": 0}, {"index": 10140, "class": 2}, {"index": 13941, "class": 2}, {"index": 9452, "class": 1}, {"index": 1845, "class": 0}, {"index": 3884, "class": 0}, {"index": 14159, "class": 2}, {"index": 1087, "class": 0}, {"index": 8348, "class": 1}, {"index": 5490, "class": 1}, {"index": 12782, "class": 2}, {"index": 8730, "class": 1}, {"index": 14108, "class": 2}, {"index": 5908, "class": 1}, {"index": 36, "class": 0}, {"index": 4014, "class": 0}, {"index": 990, "class": 0}, {"index": 486, "class": 0}, {"index": 14427, "class": 2}, {"index": 13076, "class": 2}, {"index": 7663, "class": 1}, {"index": 2784, "class": 0}, {"index": 2832, "class": 0}, {"index": 12010, "class": 2}, {"index": 10220, "class": 2}, {"index": 4558, "class": 0}, {"index": 5728, "class": 1}, {"index": 4364, "class": 0}, {"index": 8113, "class": 1}, {"index": 11304, "class": 2}, {"index": 14381, "class": 2}, {"index": 1245, "class": 0}, {"index": 13431, "class": 2}, {"index": 180, "class": 0}, {"index": 9987, "class": 2}, {"index": 10331, "class": 2}, {"index": 7372, "class": 1}, {"index": 7193, "class": 1}, {"index": 8816, "class": 1}, {"index": 1360, "class": 0}, {"index": 3791, "class": 0}, {"index": 10946, "class": 2}, {"index": 3890, "class": 0}, {"index": 8542, "class": 1}, {"index": 1389, "class": 0}, {"index": 3290, "class": 0}, {"index": 5372, "class": 1}, {"index": 11623, "class": 2}, {"index": 13010, "class": 2}, {"index": 2959, "class": 0}, {"index": 755, "class": 0}, {"index": 8470, "class": 1}, {"index": 686, "class": 0}, {"index": 11505, "class": 2}, {"index": 9022, "class": 1}, {"index": 374, "class": 0}, {"index": 6976, "class": 1}, {"index": 9849, "class": 1}, {"index": 5965, "class": 1}, {"index": 8591, "class": 1}, {"index": 6830, "class": 1}, {"index": 3749, "class": 0}, {"index": 11048, "class": 2}, {"index": 12478, "class": 2}, {"index": 6203, "class": 1}, {"index": 6743, "class": 1}, {"index": 2276, "class": 0}, {"index": 7415, "class": 1}, {"index": 11485, "class": 2}, {"index": 12293, "class": 2}, {"index": 11203, "class": 2}, {"index": 6502, "class": 1}, {"index": 2892, "class": 0}, {"index": 4986, "class": 0}, {"index": 13289, "class": 2}, {"index": 6802, "class": 1}, {"index": 3940, "class": 0}, {"index": 5132, "class": 0}, {"index": 14279, "class": 2}, {"index": 8742, "class": 1}, {"index": 9529, "class": 1}, {"index": 826, "class": 0}, {"index": 11334, "class": 2}, {"index": 4340, "class": 0}, {"index": 7180, "class": 1}, {"index": 9929, "class": 2}, {"index": 14222, "class": 2}, {"index": 2729, "class": 0}, {"index": 13556, "class": 2}, {"index": 10052, "class": 2}, {"index": 5857, "class": 1}, {"index": 9486, "class": 1}, {"index": 11817, "class": 2}, {"index": 12840, "class": 2}, {"index": 7777, "class": 1}, {"index": 746, "class": 0}, {"index": 6696, "class": 1}, {"index": 5928, "class": 1}, {"index": 10163, "class": 2}, {"index": 13665, "class": 2}, {"index": 2696, "class": 0}, {"index": 3909, "class": 0}, {"index": 11006, "class": 2}, {"index": 2405, "class": 0}, {"index": 5025, "class": 0}, {"index": 11039, "class": 2}, {"index": 14560, "class": 2}, {"index": 3991, "class": 0}, {"index": 10127, "class": 2}, {"index": 6565, "class": 1}, {"index": 7435, "class": 1}, {"index": 1351, "class": 0}, {"index": 1936, "class": 0}, {"index": 13768, "class": 2}, {"index": 12089, "class": 2}, {"index": 3964, "class": 0}, {"index": 12830, "class": 2}, {"index": 7880, "class": 1}, {"index": 9615, "class": 1}, {"index": 7842, "class": 1}, {"index": 382, "class": 0}, {"index": 12298, "class": 2}, {"index": 4479, "class": 0}, {"index": 10688, "class": 2}, {"index": 10604, "class": 2}, {"index": 8722, "class": 1}, {"index": 510, "class": 0}, {"index": 9756, "class": 1}, {"index": 5526, "class": 1}, {"index": 10872, "class": 2}, {"index": 9040, "class": 1}, {"index": 4943, "class": 0}, {"index": 9823, "class": 1}, {"index": 1833, "class": 0}, {"index": 9210, "class": 1}, {"index": 108, "class": 0}, {"index": 7618, "class": 1}, {"index": 8902, "class": 1}, {"index": 2880, "class": 0}, {"index": 13308, "class": 2}, {"index": 8111, "class": 1}, {"index": 5127, "class": 0}, {"index": 10469, "class": 2}, {"index": 7131, "class": 1}, {"index": 191, "class": 0}, {"index": 5685, "class": 1}, {"index": 4966, "class": 0}, {"index": 7326, "class": 1}, {"index": 7591, "class": 1}, {"index": 529, "class": 0}, {"index": 3023, "class": 0}, {"index": 13651, "class": 2}, {"index": 12918, "class": 2}, {"index": 10358, "class": 2}, {"index": 10460, "class": 2}, {"index": 1738, "class": 0}, {"index": 4753, "class": 0}, {"index": 2874, "class": 0}, {"index": 4205, "class": 0}, {"index": 898, "class": 0}, {"index": 9642, "class": 1}, {"index": 8466, "class": 1}, {"index": 14540, "class": 2}, {"index": 4026, "class": 0}, {"index": 416, "class": 0}, {"index": 12637, "class": 2}, {"index": 259, "class": 0}, {"index": 11166, "class": 2}, {"index": 5485, "class": 1}, {"index": 1499, "class": 0}, {"index": 1547, "class": 0}, {"index": 14358, "class": 2}, {"index": 14588, "class": 2}, {"index": 14052, "class": 2}, {"index": 1958, "class": 0}, {"index": 2362, "class": 0}, {"index": 11413, "class": 2}, {"index": 14353, "class": 2}, {"index": 4940, "class": 0}, {"index": 7407, "class": 1}, {"index": 10013, "class": 2}, {"index": 3206, "class": 0}, {"index": 1909, "class": 0}, {"index": 4375, "class": 0}, {"index": 11440, "class": 2}, {"index": 8564, "class": 1}, {"index": 9974, "class": 2}, {"index": 10725, "class": 2}, {"index": 3840, "class": 0}, {"index": 7822, "class": 1}, {"index": 11806, "class": 2}, {"index": 12451, "class": 2}, {"index": 5178, "class": 1}, {"index": 1283, "class": 0}, {"index": 13168, "class": 2}, {"index": 1019, "class": 0}, {"index": 6113, "class": 1}, {"index": 6189, "class": 1}, {"index": 14458, "class": 2}, {"index": 5077, "class": 0}, {"index": 8697, "class": 1}, {"index": 1841, "class": 0}, {"index": 12552, "class": 2}, {"index": 950, "class": 0}, {"index": 2542, "class": 0}, {"index": 3025, "class": 0}, {"index": 9183, "class": 1}, {"index": 7942, "class": 1}, {"index": 2265, "class": 0}, {"index": 10150, "class": 2}, {"index": 5028, "class": 0}, {"index": 9215, "class": 1}, {"index": 11665, "class": 2}, {"index": 6594, "class": 1}, {"index": 810, "class": 0}, {"index": 9841, "class": 1}, {"index": 9450, "class": 1}, {"index": 204, "class": 0}, {"index": 2825, "class": 0}, {"index": 8239, "class": 1}, {"index": 7909, "class": 1}, {"index": 5412, "class": 1}, {"index": 12888, "class": 2}, {"index": 14410, "class": 2}, {"index": 8994, "class": 1}, {"index": 6427, "class": 1}, {"index": 7915, "class": 1}, {"index": 975, "class": 0}, {"index": 9090, "class": 1}, {"index": 4090, "class": 0}, {"index": 1610, "class": 0}, {"index": 5216, "class": 1}, {"index": 10359, "class": 2}, {"index": 7786, "class": 1}, {"index": 10814, "class": 2}, {"index": 12347, "class": 2}, {"index": 8869, "class": 1}, {"index": 12055, "class": 2}, {"index": 12419, "class": 2}, {"index": 4909, "class": 0}, {"index": 9018, "class": 1}, {"index": 9580, "class": 1}, {"index": 11470, "class": 2}, {"index": 14537, "class": 2}, {"index": 1467, "class": 0}, {"index": 14494, "class": 2}, {"index": 4172, "class": 0}, {"index": 3057, "class": 0}, {"index": 11258, "class": 2}, {"index": 12774, "class": 2}, {"index": 561, "class": 0}, {"index": 1507, "class": 0}, {"index": 8016, "class": 1}, {"index": 6527, "class": 1}, {"index": 7827, "class": 1}, {"index": 12623, "class": 2}, {"index": 1709, "class": 0}, {"index": 3558, "class": 0}, {"index": 9762, "class": 1}, {"index": 12748, "class": 2}, {"index": 10000, "class": 2}, {"index": 3757, "class": 0}, {"index": 6104, "class": 1}, {"index": 4337, "class": 0}, {"index": 10083, "class": 2}, {"index": 8682, "class": 1}, {"index": 7945, "class": 1}, {"index": 13003, "class": 2}, {"index": 14069, "class": 2}, {"index": 347, "class": 0}, {"index": 3144, "class": 0}, {"index": 8423, "class": 1}, {"index": 2439, "class": 0}, {"index": 3533, "class": 0}, {"index": 2316, "class": 0}, {"index": 1254, "class": 0}, {"index": 12180, "class": 2}, {"index": 992, "class": 0}, {"index": 2056, "class": 0}, {"index": 11825, "class": 2}, {"index": 9896, "class": 2}, {"index": 6238, "class": 1}, {"index": 13194, "class": 2}, {"index": 1994, "class": 0}, {"index": 8429, "class": 1}, {"index": 7898, "class": 1}, {"index": 5581, "class": 1}, {"index": 2804, "class": 0}, {"index": 451, "class": 0}, {"index": 170, "class": 0}, {"index": 8304, "class": 1}, {"index": 9430, "class": 1}, {"index": 3091, "class": 0}, {"index": 6318, "class": 1}, {"index": 2584, "class": 0}, {"index": 2990, "class": 0}, {"index": 12489, "class": 2}, {"index": 6320, "class": 1}, {"index": 5814, "class": 1}, {"index": 8376, "class": 1}, {"index": 12582, "class": 2}, {"index": 10876, "class": 2}, {"index": 10436, "class": 2}, {"index": 10802, "class": 2}, {"index": 9981, "class": 2}, {"index": 3636, "class": 0}, {"index": 1377, "class": 0}, {"index": 13305, "class": 2}, {"index": 4423, "class": 0}, {"index": 9508, "class": 1}, {"index": 304, "class": 0}, {"index": 10808, "class": 2}, {"index": 5517, "class": 1}, {"index": 7532, "class": 1}, {"index": 4973, "class": 0}, {"index": 9263, "class": 1}, {"index": 3771, "class": 0}, {"index": 912, "class": 0}, {"index": 14577, "class": 2}, {"index": 11818, "class": 2}, {"index": 4231, "class": 0}, {"index": 13358, "class": 2}, {"index": 8608, "class": 1}, {"index": 9378, "class": 1}, {"index": 6979, "class": 1}, {"index": 5108, "class": 0}, {"index": 6470, "class": 1}, {"index": 1088, "class": 0}, {"index": 9285, "class": 1}, {"index": 10089, "class": 2}, {"index": 13263, "class": 2}, {"index": 9681, "class": 1}, {"index": 7293, "class": 1}, {"index": 6052, "class": 1}, {"index": 8574, "class": 1}, {"index": 11947, "class": 2}, {"index": 3369, "class": 0}, {"index": 8203, "class": 1}, {"index": 9104, "class": 1}, {"index": 14486, "class": 2}, {"index": 6327, "class": 1}, {"index": 6038, "class": 1}, {"index": 5865, "class": 1}, {"index": 4590, "class": 0}, {"index": 1828, "class": 0}, {"index": 3608, "class": 0}, {"index": 12959, "class": 2}, {"index": 9035, "class": 1}, {"index": 1404, "class": 0}, {"index": 4155, "class": 0}, {"index": 8865, "class": 1}, {"index": 12356, "class": 2}, {"index": 10225, "class": 2}, {"index": 3665, "class": 0}, {"index": 13173, "class": 2}, {"index": 14129, "class": 2}, {"index": 5318, "class": 1}, {"index": 1860, "class": 0}, {"index": 14023, "class": 2}, {"index": 11519, "class": 2}, {"index": 13514, "class": 2}, {"index": 8097, "class": 1}, {"index": 7694, "class": 1}, {"index": 8211, "class": 1}, {"index": 5294, "class": 1}, {"index": 10272, "class": 2}, {"index": 9658, "class": 1}, {"index": 9624, "class": 1}, {"index": 11729, "class": 2}, {"index": 5566, "class": 1}, {"index": 1926, "class": 0}, {"index": 888, "class": 0}, {"index": 11531, "class": 2}, {"index": 4793, "class": 0}, {"index": 5674, "class": 1}, {"index": 4968, "class": 0}, {"index": 13071, "class": 2}, {"index": 601, "class": 0}, {"index": 6910, "class": 1}, {"index": 9085, "class": 1}, {"index": 1571, "class": 0}, {"index": 10306, "class": 2}, {"index": 2660, "class": 0}, {"index": 5910, "class": 1}, {"index": 4786, "class": 0}, {"index": 1767, "class": 0}, {"index": 11243, "class": 2}, {"index": 7378, "class": 1}, {"index": 4824, "class": 0}, {"index": 5161, "class": 1}, {"index": 13900, "class": 2}, {"index": 5110, "class": 0}, {"index": 8545, "class": 1}, {"index": 9113, "class": 1}, {"index": 1412, "class": 0}, {"index": 14219, "class": 2}, {"index": 9363, "class": 1}, {"index": 9975, "class": 2}, {"index": 12250, "class": 2}, {"index": 3444, "class": 0}, {"index": 11331, "class": 2}, {"index": 14370, "class": 2}, {"index": 5563, "class": 1}, {"index": 7134, "class": 1}, {"index": 1979, "class": 0}, {"index": 5282, "class": 1}, {"index": 10933, "class": 2}, {"index": 6417, "class": 1}, {"index": 9544, "class": 1}, {"index": 1466, "class": 0}, {"index": 8019, "class": 1}, {"index": 14182, "class": 2}, {"index": 10949, "class": 2}, {"index": 11804, "class": 2}, {"index": 5341, "class": 1}, {"index": 11371, "class": 2}, {"index": 10259, "class": 2}, {"index": 1306, "class": 0}, {"index": 497, "class": 0}, {"index": 783, "class": 0}, {"index": 2002, "class": 0}, {"index": 12381, "class": 2}, {"index": 2320, "class": 0}, {"index": 14197, "class": 2}, {"index": 1720, "class": 0}, {"index": 219, "class": 0}, {"index": 8346, "class": 1}, {"index": 4835, "class": 0}, {"index": 2891, "class": 0}, {"index": 421, "class": 0}, {"index": 11849, "class": 2}, {"index": 7585, "class": 1}, {"index": 13378, "class": 2}, {"index": 10728, "class": 2}, {"index": 11188, "class": 2}, {"index": 10516, "class": 2}, {"index": 12265, "class": 2}, {"index": 1166, "class": 0}, {"index": 6985, "class": 1}, {"index": 12893, "class": 2}, {"index": 12338, "class": 2}, {"index": 4679, "class": 0}, {"index": 14250, "class": 2}, {"index": 3341, "class": 0}, {"index": 8182, "class": 1}, {"index": 8562, "class": 1}, {"index": 163, "class": 0}, {"index": 13544, "class": 2}, {"index": 12547, "class": 2}, {"index": 540, "class": 0}, {"index": 7102, "class": 1}, {"index": 10819, "class": 2}, {"index": 8709, "class": 1}, {"index": 5881, "class": 1}, {"index": 3142, "class": 0}, {"index": 12277, "class": 2}, {"index": 5773, "class": 1}, {"index": 11237, "class": 2}, {"index": 5557, "class": 1}, {"index": 13523, "class": 2}, {"index": 10965, "class": 2}, {"index": 12651, "class": 2}, {"index": 10174, "class": 2}, {"index": 9225, "class": 1}, {"index": 7240, "class": 1}, {"index": 10974, "class": 2}, {"index": 35, "class": 0}, {"index": 1144, "class": 0}, {"index": 11743, "class": 2}, {"index": 10569, "class": 2}, {"index": 1372, "class": 0}, {"index": 14593, "class": 2}, {"index": 1517, "class": 0}, {"index": 709, "class": 0}, {"index": 8962, "class": 1}, {"index": 2862, "class": 0}, {"index": 9034, "class": 1}, {"index": 3875, "class": 0}, {"index": 2073, "class": 0}, {"index": 1146, "class": 0}, {"index": 2878, "class": 0}, {"index": 6151, "class": 1}, {"index": 14278, "class": 2}, {"index": 10346, "class": 2}, {"index": 14249, "class": 2}, {"index": 2068, "class": 0}, {"index": 7533, "class": 1}, {"index": 1140, "class": 0}, {"index": 1703, "class": 0}, {"index": 5696, "class": 1}, {"index": 9330, "class": 1}, {"index": 4534, "class": 0}, {"index": 3021, "class": 0}, {"index": 8780, "class": 1}, {"index": 1464, "class": 0}, {"index": 12026, "class": 2}, {"index": 6575, "class": 1}, {"index": 509, "class": 0}, {"index": 3214, "class": 0}, {"index": 2158, "class": 0}, {"index": 5621, "class": 1}, {"index": 7207, "class": 1}, {"index": 12708, "class": 2}, {"index": 2199, "class": 0}, {"index": 13290, "class": 2}, {"index": 4681, "class": 0}, {"index": 953, "class": 0}, {"index": 11732, "class": 2}, {"index": 8317, "class": 1}, {"index": 6846, "class": 1}, {"index": 12217, "class": 2}, {"index": 796, "class": 0}, {"index": 7331, "class": 1}, {"index": 8663, "class": 1}, {"index": 4930, "class": 0}, {"index": 10400, "class": 2}, {"index": 6454, "class": 1}, {"index": 7833, "class": 1}, {"index": 12322, "class": 2}, {"index": 5887, "class": 1}, {"index": 5319, "class": 1}, {"index": 8606, "class": 1}, {"index": 8765, "class": 1}, {"index": 10881, "class": 2}, {"index": 9029, "class": 1}, {"index": 10428, "class": 2}, {"index": 5457, "class": 1}, {"index": 9247, "class": 1}, {"index": 837, "class": 0}, {"index": 12003, "class": 2}, {"index": 14099, "class": 2}, {"index": 380, "class": 0}, {"index": 3773, "class": 0}, {"index": 7403, "class": 1}, {"index": 566, "class": 0}, {"index": 6856, "class": 1}, {"index": 11951, "class": 2}, {"index": 7345, "class": 1}, {"index": 5032, "class": 0}, {"index": 129, "class": 0}, {"index": 6378, "class": 1}, {"index": 2346, "class": 0}, {"index": 9124, "class": 1}, {"index": 6168, "class": 1}, {"index": 866, "class": 0}, {"index": 6051, "class": 1}, {"index": 3968, "class": 0}, {"index": 2687, "class": 0}, {"index": 10029, "class": 2}, {"index": 1353, "class": 0}, {"index": 976, "class": 0}, {"index": 4698, "class": 0}, {"index": 11645, "class": 2}, {"index": 11688, "class": 2}, {"index": 4152, "class": 0}, {"index": 1241, "class": 0}, {"index": 13223, "class": 2}, {"index": 1689, "class": 0}, {"index": 13155, "class": 2}, {"index": 13072, "class": 2}, {"index": 2943, "class": 0}, {"index": 11589, "class": 2}, {"index": 12902, "class": 2}, {"index": 6990, "class": 1}, {"index": 6780, "class": 1}, {"index": 4676, "class": 0}, {"index": 6773, "class": 1}, {"index": 95, "class": 0}, {"index": 1418, "class": 0}, {"index": 9211, "class": 1}, {"index": 12410, "class": 2}, {"index": 4160, "class": 0}, {"index": 12144, "class": 2}, {"index": 10042, "class": 2}, {"index": 5441, "class": 1}, {"index": 995, "class": 0}, {"index": 4741, "class": 0}, {"index": 7051, "class": 1}, {"index": 4537, "class": 0}, {"index": 4191, "class": 0}, {"index": 12248, "class": 2}, {"index": 5109, "class": 0}, {"index": 2914, "class": 0}, {"index": 3713, "class": 0}, {"index": 3315, "class": 0}, {"index": 13905, "class": 2}, {"index": 4861, "class": 0}, {"index": 1332, "class": 0}, {"index": 10899, "class": 2}, {"index": 3177, "class": 0}, {"index": 654, "class": 0}, {"index": 12094, "class": 2}, {"index": 778, "class": 0}, {"index": 8766, "class": 1}, {"index": 4251, "class": 0}, {"index": 1919, "class": 0}, {"index": 13445, "class": 2}, {"index": 8576, "class": 1}, {"index": 1818, "class": 0}, {"index": 9590, "class": 1}, {"index": 3295, "class": 0}, {"index": 9303, "class": 1}, {"index": 110, "class": 0}, {"index": 1, "class": 0}, {"index": 3362, "class": 0}, {"index": 1210, "class": 0}, {"index": 7573, "class": 1}, {"index": 14611, "class": 2}, {"index": 5911, "class": 1}, {"index": 3423, "class": 0}, {"index": 12617, "class": 2}, {"index": 6899, "class": 1}, {"index": 920, "class": 0}, {"index": 13655, "class": 2}, {"index": 3213, "class": 0}, {"index": 6091, "class": 1}, {"index": 7037, "class": 1}, {"index": 12260, "class": 2}, {"index": 3979, "class": 0}, {"index": 1227, "class": 0}, {"index": 13562, "class": 2}, {"index": 8468, "class": 1}, {"index": 337, "class": 0}, {"index": 13286, "class": 2}, {"index": 8856, "class": 1}, {"index": 6849, "class": 1}, {"index": 276, "class": 0}, {"index": 9012, "class": 1}, {"index": 13009, "class": 2}, {"index": 3227, "class": 0}, {"index": 5393, "class": 1}, {"index": 1923, "class": 0}, {"index": 3876, "class": 0}, {"index": 7114, "class": 1}, {"index": 13740, "class": 2}, {"index": 1358, "class": 0}, {"index": 7993, "class": 1}, {"index": 4960, "class": 0}, {"index": 5830, "class": 1}, {"index": 12949, "class": 2}, {"index": 2544, "class": 0}, {"index": 6198, "class": 1}, {"index": 6413, "class": 1}, {"index": 4612, "class": 0}, {"index": 10996, "class": 2}, {"index": 5848, "class": 1}, {"index": 14117, "class": 2}, {"index": 458, "class": 0}, {"index": 745, "class": 0}, {"index": 12405, "class": 2}, {"index": 1984, "class": 0}, {"index": 6666, "class": 1}, {"index": 3817, "class": 0}, {"index": 5384, "class": 1}, {"index": 3949, "class": 0}, {"index": 2630, "class": 0}, {"index": 6298, "class": 1}, {"index": 7312, "class": 1}, {"index": 14430, "class": 2}, {"index": 14492, "class": 2}, {"index": 11059, "class": 2}, {"index": 7044, "class": 1}, {"index": 344, "class": 0}, {"index": 7505, "class": 1}, {"index": 10434, "class": 2}, {"index": 1479, "class": 0}, {"index": 8413, "class": 1}, {"index": 6998, "class": 1}, {"index": 4351, "class": 0}, {"index": 7668, "class": 1}, {"index": 2486, "class": 0}, {"index": 14095, "class": 2}, {"index": 536, "class": 0}, {"index": 7185, "class": 1}, {"index": 7373, "class": 1}, {"index": 2684, "class": 0}, {"index": 2106, "class": 0}, {"index": 12849, "class": 2}, {"index": 7563, "class": 1}, {"index": 3566, "class": 0}, {"index": 2214, "class": 0}, {"index": 7427, "class": 1}, {"index": 1417, "class": 0}, {"index": 12160, "class": 2}, {"index": 14102, "class": 2}, {"index": 11986, "class": 2}, {"index": 889, "class": 0}, {"index": 11307, "class": 2}, {"index": 11634, "class": 2}, {"index": 3382, "class": 0}, {"index": 7072, "class": 1}, {"index": 1005, "class": 0}, {"index": 3718, "class": 0}, {"index": 10534, "class": 2}, {"index": 8195, "class": 1}, {"index": 10627, "class": 2}, {"index": 6669, "class": 1}, {"index": 10488, "class": 2}, {"index": 2685, "class": 0}, {"index": 410, "class": 0}, {"index": 2321, "class": 0}, {"index": 1419, "class": 0}, {"index": 4683, "class": 0}, {"index": 2554, "class": 0}, {"index": 13741, "class": 2}, {"index": 3832, "class": 0}, {"index": 1357, "class": 0}, {"index": 10917, "class": 2}, {"index": 2424, "class": 0}, {"index": 4855, "class": 0}, {"index": 2807, "class": 0}, {"index": 10142, "class": 2}, {"index": 9224, "class": 1}, {"index": 14368, "class": 2}, {"index": 11456, "class": 2}, {"index": 1066, "class": 0}, {"index": 4356, "class": 0}, {"index": 7321, "class": 1}, {"index": 11662, "class": 2}, {"index": 7968, "class": 1}, {"index": 2366, "class": 0}, {"index": 4167, "class": 0}, {"index": 4323, "class": 0}, {"index": 8299, "class": 1}, {"index": 5362, "class": 1}, {"index": 1110, "class": 0}, {"index": 11739, "class": 2}, {"index": 12853, "class": 2}, {"index": 893, "class": 0}, {"index": 2009, "class": 0}, {"index": 11933, "class": 2}, {"index": 867, "class": 0}, {"index": 2585, "class": 0}, {"index": 13802, "class": 2}, {"index": 3149, "class": 0}, {"index": 11919, "class": 2}, {"index": 10903, "class": 2}, {"index": 12501, "class": 2}, {"index": 10941, "class": 2}, {"index": 6606, "class": 1}, {"index": 12550, "class": 2}, {"index": 4299, "class": 0}, {"index": 12391, "class": 2}, {"index": 5475, "class": 1}, {"index": 8622, "class": 1}, {"index": 7333, "class": 1}, {"index": 3083, "class": 0}, {"index": 1705, "class": 0}, {"index": 9387, "class": 1}, {"index": 6620, "class": 1}, {"index": 7305, "class": 1}, {"index": 4035, "class": 0}, {"index": 7965, "class": 1}, {"index": 14527, "class": 2}, {"index": 13832, "class": 2}, {"index": 3070, "class": 0}, {"index": 5118, "class": 0}, {"index": 6132, "class": 1}, {"index": 7636, "class": 1}, {"index": 3250, "class": 0}, {"index": 8407, "class": 1}, {"index": 2309, "class": 0}, {"index": 7674, "class": 1}, {"index": 828, "class": 0}, {"index": 14231, "class": 2}, {"index": 3643, "class": 0}, {"index": 338, "class": 0}, {"index": 4285, "class": 0}, {"index": 14137, "class": 2}, {"index": 12321, "class": 2}, {"index": 7183, "class": 1}, {"index": 10825, "class": 2}, {"index": 12078, "class": 2}, {"index": 8761, "class": 1}, {"index": 341, "class": 0}, {"index": 13925, "class": 2}, {"index": 493, "class": 0}, {"index": 8008, "class": 1}, {"index": 13831, "class": 2}, {"index": 8548, "class": 1}, {"index": 9284, "class": 1}, {"index": 10963, "class": 2}, {"index": 4413, "class": 0}, {"index": 12252, "class": 2}, {"index": 6791, "class": 1}, {"index": 2847, "class": 0}, {"index": 223, "class": 0}, {"index": 1057, "class": 0}, {"index": 526, "class": 0}, {"index": 7124, "class": 1}, {"index": 8837, "class": 1}, {"index": 8567, "class": 1}, {"index": 12803, "class": 2}, {"index": 1400, "class": 0}, {"index": 5019, "class": 0}, {"index": 3710, "class": 0}, {"index": 1067, "class": 0}, {"index": 1790, "class": 0}, {"index": 11545, "class": 2}, {"index": 1749, "class": 0}, {"index": 4010, "class": 0}, {"index": 7067, "class": 1}, {"index": 7315, "class": 1}, {"index": 8086, "class": 1}, {"index": 4108, "class": 0}, {"index": 7205, "class": 1}, {"index": 8459, "class": 1}, {"index": 14248, "class": 2}, {"index": 13804, "class": 2}, {"index": 4667, "class": 0}, {"index": 14620, "class": 2}, {"index": 4682, "class": 0}, {"index": 13643, "class": 2}, {"index": 11946, "class": 2}, {"index": 4799, "class": 0}, {"index": 9596, "class": 1}, {"index": 12306, "class": 2}, {"index": 1933, "class": 0}, {"index": 13319, "class": 2}, {"index": 8358, "class": 1}, {"index": 13355, "class": 2}, {"index": 11535, "class": 2}, {"index": 885, "class": 0}, {"index": 5102, "class": 0}, {"index": 13803, "class": 2}, {"index": 10045, "class": 2}, {"index": 12971, "class": 2}, {"index": 2340, "class": 0}, {"index": 5626, "class": 1}, {"index": 1335, "class": 0}, {"index": 10262, "class": 2}, {"index": 439, "class": 0}, {"index": 7949, "class": 1}, {"index": 1564, "class": 0}, {"index": 605, "class": 0}, {"index": 10552, "class": 2}, {"index": 4778, "class": 0}, {"index": 11939, "class": 2}, {"index": 4345, "class": 0}, {"index": 6045, "class": 1}, {"index": 5736, "class": 1}, {"index": 3358, "class": 0}, {"index": 607, "class": 0}, {"index": 3350, "class": 0}, {"index": 9570, "class": 1}, {"index": 6763, "class": 1}, {"index": 13960, "class": 2}, {"index": 6712, "class": 1}, {"index": 14470, "class": 2}, {"index": 7908, "class": 1}, {"index": 11311, "class": 2}, {"index": 13730, "class": 2}, {"index": 10583, "class": 2}, {"index": 12499, "class": 2}, {"index": 8444, "class": 1}, {"index": 14121, "class": 2}, {"index": 6083, "class": 1}, {"index": 11083, "class": 2}, {"index": 1950, "class": 0}, {"index": 3484, "class": 0}, {"index": 14608, "class": 2}, {"index": 3456, "class": 0}, {"index": 10882, "class": 2}, {"index": 9820, "class": 1}, {"index": 6330, "class": 1}, {"index": 8820, "class": 1}, {"index": 2133, "class": 0}, {"index": 9610, "class": 1}, {"index": 2949, "class": 0}, {"index": 7458, "class": 1}, {"index": 3288, "class": 0}, {"index": 1302, "class": 0}, {"index": 1409, "class": 0}, {"index": 8227, "class": 1}, {"index": 6530, "class": 1}, {"index": 9376, "class": 1}, {"index": 30, "class": 0}, {"index": 11100, "class": 2}, {"index": 8763, "class": 1}, {"index": 8366, "class": 1}, {"index": 6613, "class": 1}, {"index": 9026, "class": 1}, {"index": 12908, "class": 2}, {"index": 4790, "class": 0}, {"index": 2603, "class": 0}, {"index": 6440, "class": 1}, {"index": 13991, "class": 2}, {"index": 2703, "class": 0}, {"index": 8972, "class": 1}, {"index": 14012, "class": 2}, {"index": 2896, "class": 0}, {"index": 11302, "class": 2}, {"index": 9637, "class": 1}, {"index": 2539, "class": 0}, {"index": 6058, "class": 1}, {"index": 5056, "class": 0}, {"index": 7409, "class": 1}, {"index": 8681, "class": 1}, {"index": 7467, "class": 1}, {"index": 2972, "class": 0}, {"index": 13441, "class": 2}, {"index": 10010, "class": 2}, {"index": 10397, "class": 2}, {"index": 14541, "class": 2}, {"index": 874, "class": 0}, {"index": 4425, "class": 0}, {"index": 4675, "class": 0}, {"index": 4998, "class": 0}, {"index": 1614, "class": 0}, {"index": 1425, "class": 0}, {"index": 11326, "class": 2}, {"index": 14123, "class": 2}, {"index": 10351, "class": 2}, {"index": 4410, "class": 0}, {"index": 3602, "class": 0}, {"index": 14545, "class": 2}, {"index": 13171, "class": 2}, {"index": 13505, "class": 2}, {"index": 3667, "class": 0}, {"index": 349, "class": 0}, {"index": 9758, "class": 1}, {"index": 3989, "class": 0}, {"index": 4307, "class": 0}, {"index": 7609, "class": 1}, {"index": 13928, "class": 2}, {"index": 904, "class": 0}, {"index": 2575, "class": 0}, {"index": 1121, "class": 0}, {"index": 3639, "class": 0}, {"index": 5915, "class": 1}, {"index": 10547, "class": 2}, {"index": 4390, "class": 0}, {"index": 5170, "class": 1}, {"index": 1056, "class": 0}, {"index": 9495, "class": 1}, {"index": 4913, "class": 0}, {"index": 10023, "class": 2}, {"index": 12374, "class": 2}, {"index": 3058, "class": 0}, {"index": 13361, "class": 2}, {"index": 9276, "class": 1}, {"index": 9893, "class": 2}, {"index": 3353, "class": 0}, {"index": 13554, "class": 2}, {"index": 1911, "class": 0}, {"index": 11595, "class": 2}, {"index": 984, "class": 0}, {"index": 13557, "class": 2}, {"index": 642, "class": 0}, {"index": 6285, "class": 1}, {"index": 9272, "class": 1}, {"index": 5245, "class": 1}, {"index": 13063, "class": 2}, {"index": 9306, "class": 1}, {"index": 12597, "class": 2}, {"index": 6120, "class": 1}, {"index": 8461, "class": 1}, {"index": 4034, "class": 0}, {"index": 10530, "class": 2}, {"index": 5320, "class": 1}, {"index": 7831, "class": 1}, {"index": 5932, "class": 1}, {"index": 2072, "class": 0}, {"index": 11405, "class": 2}, {"index": 7050, "class": 1}, {"index": 1863, "class": 0}, {"index": 3882, "class": 0}, {"index": 5943, "class": 1}, {"index": 13225, "class": 2}, {"index": 5447, "class": 1}, {"index": 3693, "class": 0}, {"index": 10565, "class": 2}, {"index": 5737, "class": 1}, {"index": 244, "class": 0}, {"index": 97, "class": 0}, {"index": 86, "class": 0}, {"index": 13996, "class": 2}, {"index": 12069, "class": 2}, {"index": 9609, "class": 1}, {"index": 11430, "class": 2}, {"index": 11386, "class": 2}, {"index": 7384, "class": 1}, {"index": 4797, "class": 0}, {"index": 2732, "class": 0}, {"index": 10896, "class": 2}, {"index": 6344, "class": 1}, {"index": 4470, "class": 0}, {"index": 5689, "class": 1}, {"index": 4821, "class": 0}, {"index": 14327, "class": 2}, {"index": 13097, "class": 2}, {"index": 10199, "class": 2}, {"index": 4601, "class": 0}, {"index": 8993, "class": 1}, {"index": 10014, "class": 2}, {"index": 12262, "class": 2}, {"index": 10820, "class": 2}, {"index": 11379, "class": 2}, {"index": 2448, "class": 0}, {"index": 6065, "class": 1}, {"index": 7719, "class": 1}, {"index": 4829, "class": 0}, {"index": 4798, "class": 0}, {"index": 8696, "class": 1}, {"index": 405, "class": 0}, {"index": 4288, "class": 0}, {"index": 4132, "class": 0}, {"index": 6507, "class": 1}, {"index": 7031, "class": 1}, {"index": 5381, "class": 1}, {"index": 3640, "class": 0}, {"index": 11727, "class": 2}, {"index": 11540, "class": 2}, {"index": 12112, "class": 2}, {"index": 12176, "class": 2}, {"index": 4382, "class": 0}, {"index": 10913, "class": 2}, {"index": 7481, "class": 1}, {"index": 2182, "class": 0}, {"index": 13013, "class": 2}, {"index": 2688, "class": 0}, {"index": 12872, "class": 2}, {"index": 4833, "class": 0}, {"index": 3780, "class": 0}, {"index": 1512, "class": 0}, {"index": 10656, "class": 2}, {"index": 9476, "class": 1}, {"index": 1115, "class": 0}, {"index": 8087, "class": 1}, {"index": 13595, "class": 2}, {"index": 10438, "class": 2}, {"index": 684, "class": 0}, {"index": 8906, "class": 1}, {"index": 397, "class": 0}, {"index": 7996, "class": 1}, {"index": 2653, "class": 0}, {"index": 622, "class": 0}, {"index": 3073, "class": 0}, {"index": 5762, "class": 1}, {"index": 9301, "class": 1}, {"index": 11058, "class": 2}, {"index": 1835, "class": 0}, {"index": 3215, "class": 0}, {"index": 761, "class": 0}, {"index": 5593, "class": 1}, {"index": 4875, "class": 0}, {"index": 5248, "class": 1}, {"index": 2144, "class": 0}, {"index": 3900, "class": 0}, {"index": 12604, "class": 2}, {"index": 162, "class": 0}, {"index": 8120, "class": 1}, {"index": 12606, "class": 2}, {"index": 10704, "class": 2}, {"index": 3616, "class": 0}, {"index": 739, "class": 0}, {"index": 8093, "class": 1}, {"index": 7889, "class": 1}, {"index": 13039, "class": 2}, {"index": 14448, "class": 2}, {"index": 12691, "class": 2}, {"index": 5133, "class": 0}, {"index": 6145, "class": 1}, {"index": 8173, "class": 1}, {"index": 6230, "class": 1}, {"index": 13328, "class": 2}, {"index": 1029, "class": 0}, {"index": 3234, "class": 0}, {"index": 14554, "class": 2}, {"index": 9341, "class": 1}, {"index": 8811, "class": 1}, {"index": 7257, "class": 1}, {"index": 3262, "class": 0}, {"index": 8864, "class": 1}, {"index": 9925, "class": 2}, {"index": 2908, "class": 0}, {"index": 11261, "class": 2}, {"index": 1713, "class": 0}, {"index": 4643, "class": 0}, {"index": 4710, "class": 0}, {"index": 9685, "class": 1}, {"index": 10483, "class": 2}, {"index": 8823, "class": 1}, {"index": 7646, "class": 1}, {"index": 13605, "class": 2}, {"index": 3834, "class": 0}, {"index": 8240, "class": 1}, {"index": 10736, "class": 2}, {"index": 8221, "class": 1}, {"index": 8967, "class": 1}, {"index": 14571, "class": 2}, {"index": 9838, "class": 1}, {"index": 10967, "class": 2}, {"index": 438, "class": 0}, {"index": 1455, "class": 0}, {"index": 9775, "class": 1}, {"index": 8939, "class": 1}, {"index": 11410, "class": 2}, {"index": 11681, "class": 2}, {"index": 10260, "class": 2}, {"index": 456, "class": 0}, {"index": 9449, "class": 1}, {"index": 4211, "class": 0}, {"index": 6014, "class": 1}, {"index": 10717, "class": 2}, {"index": 11563, "class": 2}, {"index": 13347, "class": 2}, {"index": 8661, "class": 1}, {"index": 13503, "class": 2}, {"index": 1039, "class": 0}, {"index": 11984, "class": 2}, {"index": 13426, "class": 2}, {"index": 9069, "class": 1}, {"index": 478, "class": 0}, {"index": 907, "class": 0}, {"index": 2669, "class": 0}, {"index": 12141, "class": 2}, {"index": 13336, "class": 2}, {"index": 9991, "class": 2}, {"index": 9019, "class": 1}, {"index": 6359, "class": 1}, {"index": 1060, "class": 0}, {"index": 4346, "class": 0}, {"index": 4041, "class": 0}, {"index": 13897, "class": 2}, {"index": 4743, "class": 0}, {"index": 1233, "class": 0}, {"index": 9397, "class": 1}, {"index": 13099, "class": 2}, {"index": 7019, "class": 1}, {"index": 14032, "class": 2}, {"index": 4771, "class": 0}, {"index": 13636, "class": 2}, {"index": 12487, "class": 2}, {"index": 6180, "class": 1}, {"index": 11473, "class": 2}, {"index": 817, "class": 0}, {"index": 5124, "class": 0}, {"index": 835, "class": 0}, {"index": 11142, "class": 2}, {"index": 13231, "class": 2}, {"index": 10626, "class": 2}, {"index": 3467, "class": 0}, {"index": 4514, "class": 0}, {"index": 14591, "class": 2}, {"index": 6694, "class": 1}, {"index": 8509, "class": 1}, {"index": 8738, "class": 1}, {"index": 4656, "class": 0}, {"index": 11963, "class": 2}, {"index": 13018, "class": 2}, {"index": 3271, "class": 0}, {"index": 2798, "class": 0}, {"index": 12186, "class": 2}, {"index": 5966, "class": 1}, {"index": 2038, "class": 0}, {"index": 10158, "class": 2}, {"index": 5975, "class": 1}, {"index": 5338, "class": 1}, {"index": 12705, "class": 2}, {"index": 936, "class": 0}, {"index": 9919, "class": 2}, {"index": 11910, "class": 2}, {"index": 11546, "class": 2}, {"index": 10944, "class": 2}, {"index": 1411, "class": 0}, {"index": 6730, "class": 1}, {"index": 2307, "class": 0}, {"index": 3405, "class": 0}, {"index": 9355, "class": 1}, {"index": 3595, "class": 0}, {"index": 12963, "class": 2}, {"index": 4298, "class": 0}, {"index": 1072, "class": 0}, {"index": 7648, "class": 1}, {"index": 10393, "class": 2}, {"index": 8945, "class": 1}, {"index": 13185, "class": 2}, {"index": 6397, "class": 1}, {"index": 367, "class": 0}, {"index": 6834, "class": 1}, {"index": 12832, "class": 2}, {"index": 11213, "class": 2}, {"index": 9134, "class": 1}, {"index": 11872, "class": 2}, {"index": 3899, "class": 0}, {"index": 7836, "class": 1}, {"index": 8265, "class": 1}, {"index": 3121, "class": 0}, {"index": 13567, "class": 2}, {"index": 13836, "class": 2}, {"index": 4335, "class": 0}, {"index": 10527, "class": 2}, {"index": 12719, "class": 2}, {"index": 2470, "class": 0}, {"index": 8024, "class": 1}, {"index": 3090, "class": 0}, {"index": 14360, "class": 2}, {"index": 11242, "class": 2}, {"index": 10525, "class": 2}, {"index": 3508, "class": 0}, {"index": 9550, "class": 1}, {"index": 7747, "class": 1}, {"index": 4705, "class": 0}, {"index": 450, "class": 0}, {"index": 9456, "class": 1}, {"index": 7946, "class": 1}, {"index": 7047, "class": 1}, {"index": 4217, "class": 0}, {"index": 2790, "class": 0}, {"index": 39, "class": 0}, {"index": 13124, "class": 2}, {"index": 7977, "class": 1}, {"index": 8226, "class": 1}, {"index": 3461, "class": 0}, {"index": 233, "class": 0}, {"index": 11089, "class": 2}, {"index": 5612, "class": 1}, {"index": 8038, "class": 1}, {"index": 6000, "class": 1}, {"index": 7213, "class": 1}, {"index": 10928, "class": 2}, {"index": 9627, "class": 1}, {"index": 13414, "class": 2}, {"index": 8665, "class": 1}, {"index": 13005, "class": 2}, {"index": 941, "class": 0}, {"index": 242, "class": 0}, {"index": 670, "class": 0}, {"index": 11898, "class": 2}, {"index": 12177, "class": 2}, {"index": 3015, "class": 0}, {"index": 13545, "class": 2}, {"index": 2444, "class": 0}, {"index": 10979, "class": 2}, {"index": 9904, "class": 2}, {"index": 10511, "class": 2}, {"index": 6986, "class": 1}, {"index": 13936, "class": 2}, {"index": 12154, "class": 2}, {"index": 12066, "class": 2}, {"index": 9793, "class": 1}, {"index": 5625, "class": 1}, {"index": 80, "class": 0}, {"index": 12124, "class": 2}, {"index": 6251, "class": 1}, {"index": 11153, "class": 2}, {"index": 3972, "class": 0}, {"index": 14598, "class": 2}, {"index": 7411, "class": 1}, {"index": 4293, "class": 0}, {"index": 11882, "class": 2}, {"index": 13884, "class": 2}, {"index": 9489, "class": 1}, {"index": 11824, "class": 2}, {"index": 3498, "class": 0}, {"index": 14597, "class": 2}, {"index": 6506, "class": 1}, {"index": 2234, "class": 0}, {"index": 849, "class": 0}, {"index": 2126, "class": 0}, {"index": 8706, "class": 1}, {"index": 7627, "class": 1}, {"index": 1049, "class": 0}, {"index": 12865, "class": 2}, {"index": 4400, "class": 0}, {"index": 10190, "class": 2}, {"index": 7243, "class": 1}, {"index": 10134, "class": 2}, {"index": 11419, "class": 2}, {"index": 4548, "class": 0}, {"index": 13654, "class": 2}, {"index": 11037, "class": 2}, {"index": 2370, "class": 0}, {"index": 8148, "class": 1}, {"index": 9972, "class": 2}, {"index": 4122, "class": 0}, {"index": 7730, "class": 1}, {"index": 9782, "class": 1}, {"index": 10484, "class": 2}, {"index": 8057, "class": 1}, {"index": 517, "class": 0}, {"index": 9193, "class": 1}, {"index": 7105, "class": 1}, {"index": 5211, "class": 1}, {"index": 13093, "class": 2}, {"index": 14409, "class": 2}, {"index": 7137, "class": 1}, {"index": 13966, "class": 2}, {"index": 9567, "class": 1}, {"index": 9532, "class": 1}, {"index": 14175, "class": 2}, {"index": 7476, "class": 1}, {"index": 7400, "class": 1}, {"index": 3305, "class": 0}, {"index": 4920, "class": 0}, {"index": 13633, "class": 2}, {"index": 13434, "class": 2}, {"index": 13524, "class": 2}, {"index": 5921, "class": 1}, {"index": 6339, "class": 1}, {"index": 13692, "class": 2}]